pixelcache/__init__.py
pixelcache/main.py
pixelcache/assets/pixel_cache.png
pixelcache/assets/pixel_cache_demo_blend.jpg
pixelcache/assets/pixel_cache_demo_cropUncrop.jpg
pixelcache/examples/__init__.py
pixelcache/examples/blend.py
pixelcache/examples/crop_uncrop.py
pixelcache/fonts/JetBrainsMono-Bold.ttf
pixelcache/fonts/JetBrainsMono-BoldItalic.ttf
pixelcache/fonts/JetBrainsMono-ExtraBold.ttf
pixelcache/fonts/JetBrainsMono-ExtraBoldItalic.ttf
pixelcache/fonts/JetBrainsMono-ExtraLight.ttf
pixelcache/fonts/JetBrainsMono-ExtraLightItalic.ttf
pixelcache/fonts/JetBrainsMono-Italic.ttf
pixelcache/fonts/JetBrainsMono-Italic[wght].ttf
pixelcache/fonts/JetBrainsMono-Light.ttf
pixelcache/fonts/JetBrainsMono-LightItalic.ttf
pixelcache/fonts/JetBrainsMono-Medium.ttf
pixelcache/fonts/JetBrainsMono-MediumItalic.ttf
pixelcache/fonts/JetBrainsMono-Regular.ttf
pixelcache/fonts/JetBrainsMono-SemiBold.ttf
pixelcache/fonts/JetBrainsMono-SemiBoldItalic.ttf
pixelcache/fonts/JetBrainsMono-Thin.ttf
pixelcache/fonts/JetBrainsMono-ThinItalic.ttf
pixelcache/fonts/JetBrainsMonoNL-Bold.ttf
pixelcache/fonts/JetBrainsMonoNL-BoldItalic.ttf
pixelcache/fonts/JetBrainsMonoNL-ExtraBold.ttf
pixelcache/fonts/JetBrainsMonoNL-ExtraBoldItalic.ttf
pixelcache/fonts/JetBrainsMonoNL-ExtraLight.ttf
pixelcache/fonts/JetBrainsMonoNL-ExtraLightItalic.ttf
pixelcache/fonts/JetBrainsMonoNL-Italic.ttf
pixelcache/fonts/JetBrainsMonoNL-Light.ttf
pixelcache/fonts/JetBrainsMonoNL-LightItalic.ttf
pixelcache/fonts/JetBrainsMonoNL-Medium.ttf
pixelcache/fonts/JetBrainsMonoNL-MediumItalic.ttf
pixelcache/fonts/JetBrainsMonoNL-Regular.ttf
pixelcache/fonts/JetBrainsMonoNL-SemiBold.ttf
pixelcache/fonts/JetBrainsMonoNL-SemiBoldItalic.ttf
pixelcache/fonts/JetBrainsMonoNL-Thin.ttf
pixelcache/fonts/JetBrainsMonoNL-ThinItalic.ttf
pixelcache/fonts/JetBrainsMono[wght].ttf
pixelcache/tools/__init__.py
pixelcache/tools/bbox.py
pixelcache/tools/cache.py
pixelcache/tools/draw.py
pixelcache/tools/image.py
pixelcache/tools/keypoints.py
pixelcache-0.2.0.dist-info/METADATA
pixelcache-0.2.0.dist-info/WHEEL
pixelcache-0.2.0.dist-info/licenses/LICENSE.md
pixelcache-0.2.0.dist-info/RECORD
