Metadata-Version: 2.4
Name: pixelcache
Version: 0.2.0
Summary: A versatile image processing library for Python with built-in support for caching, using Pillow, NumPy, and PyTorch.
Author-email: Andres <me@afromero.co>
License-File: LICENSE.md
Requires-Python: ~=3.10
Requires-Dist: beartype<0.20,>=0.19.0
Requires-Dist: einops<0.9,>=0.8.0
Requires-Dist: jaxtyping<0.3,>=0.2.36
Requires-Dist: json5<0.11,>=0.10.0
Requires-Dist: numpy
Requires-Dist: opencv-python<5,>=4.10.0.84
Requires-Dist: pathlib<2,>=1.0.1
Requires-Dist: pillow<12,>=11.0.0
Requires-Dist: pydantic<3,>=2.10.2
Requires-Dist: requests<3,>=2.32.3
Requires-Dist: rich<14,>=13.9.4
Requires-Dist: torch
Requires-Dist: torchvision
Requires-Dist: tyro<0.10,>=0.9.2
